{
    "id": 4661479,
    "title": "haldir_cavern.jpg",
    "slug": null,
    "state": "public",
    "isWip": null,
    "isDraft": null,
    "entityClass": "Image",
    "icon": "fa-solid fa-image",
    "url": "https://www.worldanvil.com/uploads/images/f51bbfced1aff3d939b3899f6f064232.jpg",
    "subscribergroups": [],
    "folderId": "-1",
    "tags": "",
    "updateDate": {
        "date": "2023-07-05 11:59:18.000000",
        "timezone_type": 3,
        "timezone": "Europe/London"
    },
    "filename": "f51bbfced1aff3d939b3899f6f064232.jpg",
    "path": "/uploads/images",
    "size": 126186,
    "width": 640,
    "height": 959,
    "extension": "jpg",
    "description": null,
    "alt": null,
    "creditArtistName": "Bryce Evans",
    "creditArtistWebsite": "https://unsplash.com/@artofbryce",
    "creditArtTitle": "Haldir Living Cavern",
    "creditArtUrl": "https://unsplash.com/photos/js_D1q7Rh0M",
    "creationDate": {
        "date": "2023-07-05 11:58:21.000000",
        "timezone_type": 3,
        "timezone": "Europe/London"
    },
    "views": 94,
    "likes": null,
    "isFeatured": false,
    "linkUrl": null,
    "pageUrl": "https://www.worldanvil.com/i/4661479",
    "isEditable": true,
    "success": true
}