{
    "id": "536f1cbb-8bde-4e48-9234-4bb10ca236e6",
    "title": "Edwige Pennsworth",
    "slug": "edwige-pennsworth-person",
    "state": "public",
    "isWip": true,
    "isDraft": false,
    "entityClass": "Person",
    "icon": "fa-solid fa-user-crown",
    "url": "https://www.worldanvil.com/w/hesli/a/edwige-pennsworth-person",
    "subscribergroups": [],
    "folderId": "-1",
    "tags": "SummerCamp22,Revisit,Expand",
    "updateDate": {
        "date": "2025-01-09 11:30:39.000000",
        "timezone_type": 3,
        "timezone": "Europe/London"
    },
    "position": null,
    "excerpt": null,
    "wordcount": 632,
    "creationDate": {
        "date": "2022-07-28 19:02:06.000000",
        "timezone_type": 3,
        "timezone": "Europe/London"
    },
    "publicationDate": {
        "date": "2022-07-28 19:49:05.000000",
        "timezone_type": 3,
        "timezone": "Europe/London"
    },
    "notificationDate": {
        "date": "2022-07-28 19:52:23.000000",
        "timezone_type": 3,
        "timezone": "Europe/London"
    },
    "likes": 8,
    "views": 409,
    "userMetadata": null,
    "articleMetadata": null,
    "cssClasses": null,
    "displayCss": null,
    "templateType": "person",
    "customArticleTemplate": null,
    "editor": "code",
    "content": "Roaming the eternal plains and mountains of this world, there is only one goal: draw maps. Accompanied by her trusty friend La-de-Da-de the @[Tartoise](species:b50e909b-d71a-4913-b5e6-21c9fc65d6b2), Edwige travels far and wide to draw maps of every region and town she visits. No matter how small she may be, she always finds a way to get a good view and to make most of her travels.\r\n\r\n[quote]C'mon La-de-Da-de, we've got more maps to draw!|Edwige Pennsworth[/quote]\r\n\r\n[h2]Chaotic Cartographer[/h2]\r\nAnyone who comes across Edwige always notices two things. She has a most beautiful green scarf made of a material no one knows about, and she is absolutely nuts. No challenge is too big for this tiny halfling and her equally tiny friend.\r\n\r\nGrowing up, Edwige always had a passion for drawing. Her bubbly and chaotic personality always made its way to the paper. Whether that be in the tiny details of her drawing, or in the materials she used to create it. Edwige always found a way to put an interesting spin on her work. It has become a staple in her career as a cartographer that manifested itself from this young age. However, she never would have thought that she would become a cartographer and use her skills to help others in this way.\r\n\r\nDuring her teenage years, the halfling discovered camping. Setting up a little tent somewhere in the middle of the woods or the mountains and just absorbing the view. As the number of trips through the outdoors multiplied at a speedy rate, she began to take her drawing equipment with her to take a reminder home with her.\r\n\r\n[row][col][img:3570560][/col][col]A few trips later, Edwige made a map as she was in a region she wasn't familiar with, so she knew how to get home. It was her first toe dip into cartography and she fell in love with it head over heels. Being able to travel the world, making maps, and see all the wonders it has to offer struck a chord with Edwige. As soon as she was old enough, she attended the @[Wanderers School of Cartography](organization:8e9f8c33-48cc-44dd-a0ca-1d32987e809f).\r\n\r\nFour years later, with a certificate in hand, Edwige set out into the world. Her first work as a professional, but apprentice, cartographer was the map of @[Eshil](location:251eb80c-8462-4cd2-ae93-dbb4ecb74af8). She went on to draw many more maps, some of which have been discovered and others still need to be found.[/col][/row]\r\n\r\n[quote]Let the chaos commence!|Edwige Pennsworth[/quote]",
    "author": {
        "id": "c2798a52-1647-4e83-af08-d7ecef98b723",
        "title": "Sh4d0wPh03n1x",
        "slug": null,
        "state": null,
        "isWip": null,
        "isDraft": null,
        "entityClass": "User",
        "icon": "fa-solid fa-user",
        "url": "https://www.worldanvil.com/author/Sh4d0wPh03n1x",
        "subscribergroups": [],
        "folderId": null,
        "tags": null,
        "updateDate": null
    },
    "category": {
        "id": "fff3ebe3-9ec9-42e9-9e73-d1d30a97e1dc",
        "title": "Summer Camp 2022",
        "slug": "summer-camp-2022-category",
        "state": "public",
        "isWip": null,
        "isDraft": null,
        "entityClass": "Category",
        "icon": "fa-solid fa-folder",
        "url": "https://www.worldanvil.com/w/hesli/c/summer-camp-2022-category",
        "subscribergroups": [],
        "folderId": null,
        "tags": null,
        "updateDate": null
    },
    "world": {
        "id": "2aca1405-dcb4-4c1e-b504-a2568b53266b",
        "title": "Hesli",
        "slug": "hesli",
        "state": "public",
        "isWip": null,
        "isDraft": null,
        "entityClass": "World",
        "icon": "fa-solid fa-globe-stand",
        "url": "https://www.worldanvil.com/w/hesli",
        "subscribergroups": [
            {
                "id": "0fca8d26-7f74-455a-9ff5-d522be436867",
                "title": "Friends of the Wandering Lileon",
                "slug": null,
                "state": null,
                "entityClass": "SubscriberGroup",
                "icon": null,
                "url": null,
                "subscribergroups": []
            },
            {
                "id": "c863794d-f753-492f-b851-b0eff40acdd8",
                "title": "Gamemaster",
                "slug": null,
                "state": null,
                "entityClass": "SubscriberGroup",
                "icon": null,
                "url": null,
                "subscribergroups": []
            }
        ],
        "folderId": "-1",
        "tags": "",
        "updateDate": {
            "date": "2025-03-29 09:54:54.000000",
            "timezone_type": 3,
            "timezone": "Europe/London"
        }
    },
    "portrait": {
        "id": 3570561,
        "title": "Edwige_Portrait.png",
        "slug": null,
        "state": "public",
        "isWip": null,
        "isDraft": null,
        "entityClass": "Image",
        "icon": "fa-solid fa-image",
        "url": "https://www.worldanvil.com/uploads/images/ae924cf3e055e444ec07006ec5cad1e5.png",
        "subscribergroups": [],
        "folderId": "-1",
        "tags": "",
        "updateDate": {
            "date": "2022-07-28 19:46:05.000000",
            "timezone_type": 3,
            "timezone": "Europe/London"
        }
    },
    "cover": {
        "id": 2474159,
        "title": "Hesli Banner.png",
        "slug": null,
        "state": "public",
        "isWip": null,
        "isDraft": null,
        "entityClass": "Image",
        "icon": "fa-solid fa-image",
        "url": "https://www.worldanvil.com/uploads/images/6b66201ef8418333def9f07a89754e7d.png",
        "subscribergroups": [],
        "folderId": "-1",
        "tags": "#banner #hesli",
        "updateDate": {
            "date": "2021-07-19 16:41:25.000000",
            "timezone_type": 3,
            "timezone": "Europe/London"
        }
    },
    "coverSource": "World",
    "pronunciation": null,
    "snippet": null,
    "seeded": null,
    "sidebarcontent": null,
    "sidepanelcontenttop": null,
    "sidepanelcontent": "[b]Companion[/b][br]\r\nLa-de-Da-de, the @[Tartoise](species:b50e909b-d71a-4913-b5e6-21c9fc65d6b2)[br]\r\n[b]Maps[/b][br]\r\n[url:https://www.worldanvil.com/w/hesli-sh4d0wph03n1x/map/f94696d1-c500-4ebf-bdb2-b96ddd6931ee]Eshil[/url]",
    "sidebarcontentbottom": "[h3]Trusty Companion[/h3]\r\nDuring her travels, Edwige tripped over a rock only once. Except that it wasn't a rock, but a baby @[Tartoise](species:b50e909b-d71a-4913-b5e6-21c9fc65d6b2). When she noticed the little fella move, she couldn't leave him to his fate. Edwige tried to find the parents of the baby to no avail. She sat him on the ground and walked away, but the tartoise followed her to all his might.\r\n\r\n[quote]Well, then you'll just have to come with me! I'll name you...[br]\r\nLa-de-Da-de![br]\r\nWhat?![br]\r\nLa-de-Da-de![br]\r\nAll right, La-de-Da-de it is!|Edwige Pennsworth and her new tartoise[/quote]",
    "footnotes": null,
    "fullfooter": null,
    "authornotes": null,
    "scrapbook": null,
    "credits": null,
    "displaySidebar": true,
    "articleNext": null,
    "articlePrevious": null,
    "timeline": null,
    "prompt": null,
    "gallery": null,
    "articleParent": null,
    "block": null,
    "orgchart": null,
    "showSeeded": false,
    "webhookUpdate": false,
    "communityUpdate": false,
    "commentPlaceholder": null,
    "passcodecta": null,
    "metaTitle": null,
    "metaDescription": null,
    "subheading": null,
    "coverIsMap": false,
    "isFeaturedArticle": false,
    "isAdultContent": false,
    "isLocked": false,
    "allowComments": true,
    "allowContentCopy": false,
    "showInToc": true,
    "isEmphasized": false,
    "displayAuthor": false,
    "displayChildrenUnder": true,
    "displayTitle": true,
    "displaySheet": true,
    "competitionEntries": [
        {
            "id": 499550,
            "title": "untitled",
            "slug": null,
            "state": null,
            "isWip": null,
            "isDraft": null,
            "entityClass": "CompetitionEntry",
            "icon": "fa-solid fa-balloon",
            "url": null,
            "subscribergroups": [],
            "folderId": null,
            "tags": null,
            "updateDate": null
        }
    ],
    "badge": null,
    "fans": [
        {
            "id": "410ce308-682d-4e1e-9eb0-462e8aa10062",
            "title": "Kriltch",
            "slug": null,
            "state": null,
            "isWip": null,
            "isDraft": null,
            "entityClass": "User",
            "icon": "fa-solid fa-user",
            "url": "https://www.worldanvil.com/author/Kriltch",
            "subscribergroups": [],
            "folderId": null,
            "tags": null,
            "updateDate": null
        },
        {
            "id": "538556cd-3a86-43f1-88cf-17f15084352a",
            "title": "Mochimanoban",
            "slug": null,
            "state": null,
            "isWip": null,
            "isDraft": null,
            "entityClass": "User",
            "icon": "fa-solid fa-user",
            "url": "https://www.worldanvil.com/author/Mochimanoban",
            "subscribergroups": [],
            "folderId": null,
            "tags": null,
            "updateDate": null
        },
        {
            "id": "700c98df-5ace-4b70-bfc9-e1dcf2eea6b2",
            "title": "mirescosmo",
            "slug": null,
            "state": null,
            "isWip": null,
            "isDraft": null,
            "entityClass": "User",
            "icon": "fa-solid fa-user",
            "url": "https://www.worldanvil.com/author/mirescosmo",
            "subscribergroups": [],
            "folderId": null,
            "tags": null,
            "updateDate": null
        },
        {
            "id": "702fe4c6-fdde-4afb-82b6-f52c5c593e0c",
            "title": "AmélieIS",
            "slug": null,
            "state": null,
            "isWip": null,
            "isDraft": null,
            "entityClass": "User",
            "icon": "fa-solid fa-user",
            "url": "https://www.worldanvil.com/author/Am%C3%A9lieIS",
            "subscribergroups": [],
            "folderId": null,
            "tags": null,
            "updateDate": null
        },
        {
            "id": "8070cccf-87fd-4d2a-b46e-da8372050028",
            "title": "AwsmChimera",
            "slug": null,
            "state": null,
            "isWip": null,
            "isDraft": null,
            "entityClass": "User",
            "icon": "fa-solid fa-user",
            "url": "https://www.worldanvil.com/author/AwsmChimera",
            "subscribergroups": [],
            "folderId": null,
            "tags": null,
            "updateDate": null
        },
        {
            "id": "ac71c813-f06d-4482-8a41-413697a283e0",
            "title": "Jacob-W",
            "slug": null,
            "state": null,
            "isWip": null,
            "isDraft": null,
            "entityClass": "User",
            "icon": "fa-solid fa-user",
            "url": "https://www.worldanvil.com/author/Jacob-W",
            "subscribergroups": [],
            "folderId": null,
            "tags": null,
            "updateDate": null
        },
        {
            "id": "d7099e09-6f07-4737-9f43-98dbcd035555",
            "title": "Ilmaine",
            "slug": null,
            "state": null,
            "isWip": null,
            "isDraft": null,
            "entityClass": "User",
            "icon": "fa-solid fa-user",
            "url": "https://www.worldanvil.com/author/Ilmaine",
            "subscribergroups": [],
            "folderId": null,
            "tags": null,
            "updateDate": null
        },
        {
            "id": "da93c838-919d-4963-a48b-e4ebd0b14114",
            "title": "Hanhula",
            "slug": null,
            "state": null,
            "isWip": null,
            "isDraft": null,
            "entityClass": "User",
            "icon": "fa-solid fa-user",
            "url": "https://www.worldanvil.com/author/Hanhula",
            "subscribergroups": [],
            "folderId": null,
            "tags": null,
            "updateDate": null
        }
    ],
    "comments": [
        {
            "id": "0fe4788b-91cb-489a-8ff9-e412c6f06f63",
            "title": "untitled",
            "slug": null,
            "state": "public",
            "isWip": null,
            "isDraft": null,
            "entityClass": "Comment",
            "icon": "fa-solid fa-comment",
            "url": null,
            "subscribergroups": [],
            "folderId": null,
            "tags": null,
            "updateDate": null
        },
        {
            "id": "5ddb69fc-a473-4761-9e4d-2c1144135040",
            "title": "untitled",
            "slug": null,
            "state": "public",
            "isWip": null,
            "isDraft": null,
            "entityClass": "Comment",
            "icon": "fa-solid fa-comment",
            "url": null,
            "subscribergroups": [],
            "folderId": null,
            "tags": null,
            "updateDate": null
        }
    ],
    "character": null,
    "editURL": "https://www.worldanvil.com/world/person/536f1cbb-8bde-4e48-9234-4bb10ca236e6/edit",
    "ancestry": {
        "firstUp": {
            "id": "fff3ebe3-9ec9-42e9-9e73-d1d30a97e1dc",
            "title": "Summer Camp 2022",
            "slug": "summer-camp-2022-category",
            "state": "public",
            "isWip": null,
            "isDraft": null,
            "entityClass": "Category",
            "icon": "fa-solid fa-folder",
            "url": "https://www.worldanvil.com/w/hesli/c/summer-camp-2022-category",
            "subscribergroups": [],
            "folderId": null,
            "tags": null,
            "updateDate": null
        },
        "secondUp": {
            "id": "e89cfd90-fd31-4540-b9a0-d2e3beaa7608",
            "title": "Challenges",
            "slug": "challenges-category",
            "state": "public",
            "isWip": null,
            "isDraft": null,
            "entityClass": "Category",
            "icon": "fa-solid fa-folder",
            "url": "https://www.worldanvil.com/w/hesli/c/challenges-category",
            "subscribergroups": [],
            "folderId": null,
            "tags": null,
            "updateDate": null
        },
        "thirdUp": {
            "id": "2aca1405-dcb4-4c1e-b504-a2568b53266b",
            "title": "Hesli",
            "slug": "hesli",
            "state": "public",
            "isWip": null,
            "isDraft": null,
            "entityClass": "World",
            "icon": "fa-solid fa-globe-stand",
            "url": "https://www.worldanvil.com/w/hesli",
            "subscribergroups": [
                {
                    "id": "0fca8d26-7f74-455a-9ff5-d522be436867",
                    "title": "Friends of the Wandering Lileon",
                    "slug": null,
                    "state": null,
                    "entityClass": "SubscriberGroup",
                    "icon": null,
                    "url": null,
                    "subscribergroups": []
                },
                {
                    "id": "c863794d-f753-492f-b851-b0eff40acdd8",
                    "title": "Gamemaster",
                    "slug": null,
                    "state": null,
                    "entityClass": "SubscriberGroup",
                    "icon": null,
                    "url": null,
                    "subscribergroups": []
                }
            ],
            "folderId": "-1",
            "tags": "",
            "updateDate": {
                "date": "2025-03-29 09:54:54.000000",
                "timezone_type": 3,
                "timezone": "Europe/London"
            }
        }
    },
    "firstname": null,
    "lastname": null,
    "middlename": null,
    "maidenname": null,
    "nickname": null,
    "honorific": null,
    "suffix": null,
    "dobDisplay": null,
    "dob": null,
    "dod": null,
    "dodDisplay": null,
    "age": "Unknown",
    "circumstancesBirth": null,
    "circumstancesDeath": null,
    "pronouns": "She/Her",
    "eyes": "Jolly hazel brown",
    "hair": "Short and slightly spiked brown hair",
    "skin": "Tanned",
    "height": "95cm (3'1\")",
    "birthplace": null,
    "deathplace": null,
    "residence": "Her tiny (tree)tent",
    "weight": "20kg (44lbs)",
    "gender": "Female",
    "speciesDisplay": null,
    "physique": null,
    "bodyFeatures": null,
    "facialFeatures": null,
    "identifyingCharacteristics": null,
    "quirksPhysical": null,
    "perceptionPhysical": null,
    "specialAbilities": null,
    "clothing": null,
    "items": null,
    "characterPrototype": null,
    "rpgAlignment": null,
    "deity": null,
    "currentstatus": "Mapping Hesli",
    "history": null,
    "employment": null,
    "achievements": null,
    "failures": null,
    "mentalTraumas": null,
    "intellectualCharacteristics": null,
    "morality": null,
    "taboos": null,
    "presentation": null,
    "sex": null,
    "sexuality": null,
    "genderidentity": null,
    "education": null,
    "languages": null,
    "quotes": null,
    "motivation": null,
    "savviesIneptitudes": null,
    "likesDislikes": null,
    "virtues": null,
    "vices": null,
    "quirksPersonality": null,
    "hygiene": null,
    "representationLegacy": null,
    "relations": null,
    "family": null,
    "religion": null,
    "titles": null,
    "socialAptitude": null,
    "mannerisms": null,
    "hobbies": null,
    "speech": null,
    "wealth": null,
    "classification": null,
    "domains": null,
    "codes": null,
    "holysymbols": null,
    "tenets": null,
    "goals": null,
    "holidays": null,
    "artifacts": null,
    "ggmtitle": null,
    "ggmjob": null,
    "ggmgoal": null,
    "ggmuse": null,
    "ggmgoaladditional": null,
    "ggmquirk": null,
    "ggmequipment": null,
    "ggmtype": null,
    "ggmsubtype": null,
    "ggmlikeability": null,
    "ggmcompetence": null,
    "ggmproactivity": null,
    "ggmcoolness": null,
    "ggmdesire": null,
    "ggmfear": null,
    "ggmwhyfollowing": null,
    "ggmbiography": null,
    "ggmdescfacial": null,
    "ggmdescspeech": null,
    "ggmdescbody": null,
    "ggmdescsight": null,
    "ggmdescsound": null,
    "ggmdescsmell": null,
    "ggmdesctouch": null,
    "ggmdescemotional": null,
    "ggmdeschappy": null,
    "ggmdescsad": null,
    "ggmdescangry": null,
    "reign": null,
    "datasheet": null,
    "vehicle": null,
    "parentBiological1": null,
    "parentBiological2": null,
    "parentAdopting1": null,
    "parentAdopting2": null,
    "parentSurrogate": null,
    "church": null,
    "realm": null,
    "organization": null,
    "familyorganization": null,
    "ethnicity": {
        "id": "715e9bb7-bafe-44d7-8b49-b0129356c671",
        "title": "Wanderers",
        "slug": "wanderers-ethnicity",
        "state": "public",
        "isWip": true,
        "isDraft": true,
        "entityClass": "Ethnicity",
        "icon": "fa-solid fa-file",
        "url": "https://www.worldanvil.com/w/hesli/a/wanderers-ethnicity",
        "subscribergroups": [],
        "folderId": "-1",
        "tags": "Potential",
        "updateDate": {
            "date": "2025-01-10 21:37:26.000000",
            "timezone_type": 3,
            "timezone": "Europe/London"
        }
    },
    "species": {
        "id": "70717cdd-6f6a-4769-ad5d-5bfdb1e179cd",
        "title": "Halfling",
        "slug": "halfling-species",
        "state": "public",
        "isWip": true,
        "isDraft": true,
        "entityClass": "Species",
        "icon": "fa-solid fa-file",
        "url": "https://www.worldanvil.com/w/hesli/a/halfling-species",
        "subscribergroups": [],
        "folderId": "-1",
        "tags": "Potential",
        "updateDate": {
            "date": "2025-01-23 15:37:05.000000",
            "timezone_type": 3,
            "timezone": "Europe/London"
        }
    },
    "currentLocation": null,
    "professions": [
        {
            "id": "c7a81719-7a91-4447-8706-cb2456b36289",
            "title": "Cartographer",
            "slug": "cartographer-profession",
            "state": "public",
            "isWip": true,
            "isDraft": false,
            "entityClass": "Profession",
            "icon": "fa-solid fa-file",
            "url": "https://www.worldanvil.com/w/hesli/a/cartographer-profession",
            "subscribergroups": [],
            "folderId": "0e19306e-5e1d-40cd-b899-8a87e8233a52",
            "tags": "SummerCamp23,Expand",
            "updateDate": {
                "date": "2025-01-17 14:04:00.000000",
                "timezone_type": 3,
                "timezone": "Europe/London"
            }
        }
    ],
    "documentsauthored": [
        {
            "id": "18cf71d3-4f1d-40ba-afcb-491cc83605dd",
            "title": "Edwige's Cartography Notebook",
            "slug": "edwige-s-cartography-notebook-document",
            "state": "public",
            "isWip": true,
            "isDraft": false,
            "entityClass": "Document",
            "icon": "fa-solid fa-file",
            "url": "https://www.worldanvil.com/w/hesli/a/edwige-s-cartography-notebook-document",
            "subscribergroups": [],
            "folderId": "fff3ebe3-9ec9-42e9-9e73-d1d30a97e1dc",
            "tags": "SummerCamp22,Refine,Rewrite",
            "updateDate": {
                "date": "2025-01-10 12:02:47.000000",
                "timezone_type": 3,
                "timezone": "Europe/London"
            }
        }
    ],
    "isEditable": true,
    "success": true
}